random_utilities/__init__.py
random_utilities/models/__init__.py
random_utilities/models/data.py
random_utilities/models/http_codes.py
random_utilities/models/response.py
random_utilities/models/time_created.py
random_utilities-1.0.4.dist-info/METADATA
random_utilities-1.0.4.dist-info/WHEEL
random_utilities-1.0.4.dist-info/top_level.txt
random_utilities-1.0.4.dist-info/RECORD
