Metadata-Version: 2.1
Name: random-utilities
Version: 1.0.4
Summary: Helper library for random operations
Home-page: UNKNOWN
Author: Hetchfund.Capital (Libby Lebyane)
Author-email: <lebyane.lm@gmail.com>
License: UNKNOWN
Keywords: random,utilities,tools,helpers
Platform: UNKNOWN
Requires-Dist: console
Requires-Dist: months
Requires-Dist: pymongo
Requires-Dist: pymongo[srv]
